api_to_mcp_generator/__init__.py
api_to_mcp_generator/codegen/__init__.py
api_to_mcp_generator/codegen/server_generator.py
api_to_mcp_generator/codegen/template_generator.py
api_to_mcp_generator/converter.py
api_to_mcp_generator/filter.py
api_to_mcp_generator/integrations/fastapi.py
api_to_mcp_generator/models/__init__.py
api_to_mcp_generator/models/mcp.py
api_to_mcp_generator/models/server.py
api_to_mcp_generator/parser.py
api_to_mcp_generator/resolver.py
api_to_mcp_generator/resource_generator.py
api_to_mcp_generator/utils/__init__.py
api_to_mcp_generator/utils/logging.py
api_to_mcp_generator-0.2.2.dist-info/LICENSE
api_to_mcp_generator-0.2.2.dist-info/METADATA
api_to_mcp_generator-0.2.2.dist-info/WHEEL
api_to_mcp_generator-0.2.2.dist-info/RECORD
