Metadata-Version: 2.3
Name: API-to-MCP-Generator
Version: 0.2.2
Summary: Transform any OpenAPI specification into a production-ready Model Context Protocol (MCP) server. Instantly make your REST APIs available to AI agents like Claude and GPT-4 with zero manual coding.
License: MPL-2.0
Keywords: openapi,mcp,model-context-protocol,ai,claude,gpt,fastapi,api,transformer,converter,generator
Author: Krish
Requires-Python: >=3.8,<4.0
Classifier: License :: OSI Approved
Classifier: Programming Language :: Python :: 3
Classifier: Programming Language :: Python :: 3.8
Classifier: Programming Language :: Python :: 3.9
Classifier: Programming Language :: Python :: 3.10
Classifier: Programming Language :: Python :: 3.11
Classifier: Programming Language :: Python :: 3.12
Classifier: Programming Language :: Python :: 3.13
Requires-Dist: fastapi (>=0.109.2,<0.110.0)
Requires-Dist: jsonpath-ng (>=1.5.3,<2.0.0)
Requires-Dist: jsonpointer (>=2.4,<3.0)
Requires-Dist: pydantic (>=2.0.0,<3.0.0)
Requires-Dist: pyyaml (>=6.0,<7.0)
Requires-Dist: requests (>=2.31.0,<3.0.0)
Requires-Dist: structlog (>=23.2.0,<24.0.0)
Requires-Dist: uvicorn (>=0.27.1,<0.28.0)
